file_repository_api_client/__init__.py
file_repository_api_client/file_api.py
file_repository_api_client/util.py
file_repository_api_client-0.2.2.dist-info/LICENSE
file_repository_api_client-0.2.2.dist-info/METADATA
file_repository_api_client-0.2.2.dist-info/WHEEL
file_repository_api_client-0.2.2.dist-info/top_level.txt
file_repository_api_client-0.2.2.dist-info/RECORD
